
<annotation>
    <folder>images</folder>
    <filename>hard_hat_workers382.png</filename>
    <size>
        <width>416</width>
        <height>416</height>
        <depth>3</depth>
    </size>
    <segmented>0</segmented>
    <object>
        <name>head</name>
        <pose>Unspecified</pose>
        <truncated>0</truncated>
        <occluded>0</occluded>
        <difficult>0</difficult>
        <bndbox>
            <xmin>124</xmin>
            <ymin>183</ymin>
            <xmax>153</xmax>
            <ymax>215</ymax>
        </bndbox>
    </object>
    <object>
        <name>head</name>
        <pose>Unspecified</pose>
        <truncated>0</truncated>
        <occluded>0</occluded>
        <difficult>0</difficult>
        <bndbox>
            <xmin>245</xmin>
            <ymin>161</ymin>
            <xmax>283</xmax>
            <ymax>203</ymax>
        </bndbox>
    </object>
    <object>
        <name>head</name>
        <pose>Unspecified</pose>
        <truncated>0</truncated>
        <occluded>0</occluded>
        <difficult>0</difficult>
        <bndbox>
            <xmin>88</xmin>
            <ymin>188</ymin>
            <xmax>117</xmax>
            <ymax>221</ymax>
        </bndbox>
    </object>
    <object>
        <name>head</name>
        <pose>Unspecified</pose>
        <truncated>0</truncated>
        <occluded>0</occluded>
        <difficult>0</difficult>
        <bndbox>
            <xmin>219</xmin>
            <ymin>179</ymin>
            <xmax>248</xmax>
            <ymax>213</ymax>
        </bndbox>
    </object>
    <object>
        <name>head</name>
        <pose>Unspecified</pose>
        <truncated>0</truncated>
        <occluded>0</occluded>
        <difficult>0</difficult>
        <bndbox>
            <xmin>196</xmin>
            <ymin>178</ymin>
            <xmax>224</xmax>
            <ymax>212</ymax>
        </bndbox>
    </object>
    <object>
        <name>head</name>
        <pose>Unspecified</pose>
        <truncated>0</truncated>
        <occluded>0</occluded>
        <difficult>0</difficult>
        <bndbox>
            <xmin>309</xmin>
            <ymin>182</ymin>
            <xmax>335</xmax>
            <ymax>211</ymax>
        </bndbox>
    </object>
</annotation>